{
    "parameters": {
        "category": 21,
        "db_content_name": "CAT021",
        "name": "CAT021"
    },
    "sub_configs": {
        "JSONDataMapping": {
            "JSONDataMapping1": {
                "parameters": {
                    "active": true,
                    "append_value": false,
                    "comment": "Type number, value 12880",
                    "db_content_name": "CAT021",
                    "db_content_variable_name": "DS ID",
                    "dimension": "",
                    "format_data_type": "",
                    "in_array": false,
                    "json_key": "ds_id",
                    "json_value_format": "",
                    "mandatory": false,
                    "unit": ""
                }
            },
            "JSONDataMapping100": {
                "parameters": {
                    "active": true,
                    "append_value": false,
                    "comment": "Type number, value 0.7000000000000001",
                    "db_content_name": "CAT021",
                    "db_content_variable_name": "Aircraft Identification Age",
                    "dimension": "Time",
                    "format_data_type": "",
                    "in_array": false,
                    "json_key": "295.Target Identification.Age",
                    "json_value_format": "",
                    "mandatory": false,
                    "unit": "Second"
                }
            },
            "JSONDataMapping103": {
                "parameters": {
                    "active": true,
                    "append_value": false,
                    "comment": "Type number, value 7000.0",
                    "db_content_name": "CAT021",
                    "db_content_variable_name": "Selected Altitude",
                    "dimension": "Height",
                    "format_data_type": "",
                    "in_array": false,
                    "json_key": "146.Altitude",
                    "json_value_format": "",
                    "mandatory": false,
                    "unit": "Feet"
                }
            },
            "JSONDataMapping104": {
                "parameters": {
                    "active": true,
                    "append_value": false,
                    "comment": "Type number, value 1",
                    "db_content_name": "CAT021",
                    "db_content_variable_name": "Selected Altitude Source Availability",
                    "dimension": "",
                    "format_data_type": "",
                    "in_array": false,
                    "json_key": "146.SAS",
                    "json_value_format": "",
                    "mandatory": false,
                    "unit": ""
                }
            },
            "JSONDataMapping105": {
                "parameters": {
                    "active": true,
                    "append_value": false,
                    "comment": "Type number, value 2",
                    "db_content_name": "CAT021",
                    "db_content_variable_name": "Selected Altitude Source",
                    "dimension": "",
                    "format_data_type": "",
                    "in_array": false,
                    "json_key": "146.Source",
                    "json_value_format": "",
                    "mandatory": false,
                    "unit": ""
                }
            },
            "JSONDataMapping106": {
                "parameters": {
                    "active": true,
                    "append_value": false,
                    "comment": "Type number, value 0.0",
                    "db_content_name": "CAT021",
                    "db_content_variable_name": "AOS Age",
                    "dimension": "Time",
                    "format_data_type": "",
                    "in_array": false,
                    "json_key": "295.Aircraft Operational Status.Age",
                    "json_value_format": "",
                    "mandatory": false,
                    "unit": "Second"
                }
            },
            "JSONDataMapping107": {
                "parameters": {
                    "active": true,
                    "append_value": false,
                    "comment": "Type number, value 0.4",
                    "db_content_name": "CAT021",
                    "db_content_variable_name": "Barometric Vertical Rate Age",
                    "dimension": "Time",
                    "format_data_type": "",
                    "in_array": false,
                    "json_key": "295.Barometric Vertical Rate.Age",
                    "json_value_format": "",
                    "mandatory": false,
                    "unit": "Second"
                }
            },
            "JSONDataMapping108": {
                "parameters": {
                    "active": true,
                    "append_value": false,
                    "comment": "Type number, value 0.0",
                    "db_content_name": "CAT021",
                    "db_content_variable_name": "IS SA Age",
                    "dimension": "Time",
                    "format_data_type": "",
                    "in_array": false,
                    "json_key": "295.Intermediate State Selected Altitude.Age",
                    "json_value_format": "",
                    "mandatory": false,
                    "unit": "Second"
                }
            },
            "JSONDataMapping109": {
                "parameters": {
                    "active": true,
                    "append_value": false,
                    "comment": "Type number, value 3.5",
                    "db_content_name": "CAT021",
                    "db_content_variable_name": "Mode 3/A Age",
                    "dimension": "Time",
                    "format_data_type": "",
                    "in_array": false,
                    "json_key": "295.Mode 3/A.Age",
                    "json_value_format": "",
                    "mandatory": false,
                    "unit": "Second"
                }
            },
            "JSONDataMapping110": {
                "parameters": {
                    "active": true,
                    "append_value": false,
                    "comment": "Type number, value 0.0",
                    "db_content_name": "CAT021",
                    "db_content_variable_name": "Quality Indicators Age",
                    "dimension": "Time",
                    "format_data_type": "",
                    "in_array": false,
                    "json_key": "295.Quality Indicators.Age",
                    "json_value_format": "",
                    "mandatory": false,
                    "unit": "Second"
                }
            },
            "JSONDataMapping111": {
                "parameters": {
                    "active": true,
                    "append_value": false,
                    "comment": "Type number, value 3.5",
                    "db_content_name": "CAT021",
                    "db_content_variable_name": "Target Status Age",
                    "dimension": "Time",
                    "format_data_type": "",
                    "in_array": false,
                    "json_key": "295.Target Status.Age",
                    "json_value_format": "",
                    "mandatory": false,
                    "unit": "Second"
                }
            },
            "JSONDataMapping112": {
                "parameters": {
                    "active": true,
                    "append_value": false,
                    "comment": "Type number, value 0",
                    "db_content_name": "CAT021",
                    "db_content_variable_name": "SC B2 low",
                    "dimension": "",
                    "format_data_type": "",
                    "in_array": false,
                    "json_key": "271.B2 low",
                    "json_value_format": "",
                    "mandatory": false,
                    "unit": ""
                }
            },
            "JSONDataMapping113": {
                "parameters": {
                    "active": true,
                    "append_value": false,
                    "comment": "Type number, value 1",
                    "db_content_name": "CAT021",
                    "db_content_variable_name": "SC CDTI/S",
                    "dimension": "",
                    "format_data_type": "",
                    "in_array": false,
                    "json_key": "271.CDTI/S",
                    "json_value_format": "",
                    "mandatory": false,
                    "unit": ""
                }
            },
            "JSONDataMapping115": {
                "parameters": {
                    "active": true,
                    "append_value": false,
                    "comment": "Type number, value 0",
                    "db_content_name": "CAT021",
                    "db_content_variable_name": "SC IDENT",
                    "dimension": "",
                    "format_data_type": "",
                    "in_array": false,
                    "json_key": "271.IDENT",
                    "json_value_format": "",
                    "mandatory": false,
                    "unit": ""
                }
            },
            "JSONDataMapping116": {
                "parameters": {
                    "active": true,
                    "append_value": false,
                    "comment": "Type number, value 1",
                    "db_content_name": "CAT021",
                    "db_content_variable_name": "SC L+W",
                    "dimension": "",
                    "format_data_type": "",
                    "in_array": false,
                    "json_key": "271.L+W",
                    "json_value_format": "",
                    "mandatory": false,
                    "unit": ""
                }
            },
            "JSONDataMapping117": {
                "parameters": {
                    "active": true,
                    "append_value": false,
                    "comment": "Type number, value 0",
                    "db_content_name": "CAT021",
                    "db_content_variable_name": "SC POA",
                    "dimension": "",
                    "format_data_type": "",
                    "in_array": false,
                    "json_key": "271.POA",
                    "json_value_format": "",
                    "mandatory": false,
                    "unit": ""
                }
            },
            "JSONDataMapping118": {
                "parameters": {
                    "active": true,
                    "append_value": false,
                    "comment": "Type number, value 0",
                    "db_content_name": "CAT021",
                    "db_content_variable_name": "SC RAS",
                    "dimension": "",
                    "format_data_type": "",
                    "in_array": false,
                    "json_key": "271.RAS",
                    "json_value_format": "",
                    "mandatory": false,
                    "unit": ""
                }
            },
            "JSONDataMapping119": {
                "parameters": {
                    "active": true,
                    "append_value": false,
                    "comment": "Type number, value 2.1",
                    "db_content_name": "CAT021",
                    "db_content_variable_name": "SC Age",
                    "dimension": "Time",
                    "format_data_type": "",
                    "in_array": false,
                    "json_key": "295.Surface Capabilities and Characteristics.Age",
                    "json_value_format": "",
                    "mandatory": false,
                    "unit": "Second"
                }
            },
            "JSONDataMapping12": {
                "parameters": {
                    "active": true,
                    "append_value": false,
                    "comment": "Type number, value 33825.0",
                    "db_content_name": "CAT021",
                    "db_content_variable_name": "Geometric Height",
                    "dimension": "Height",
                    "format_data_type": "",
                    "in_array": false,
                    "json_key": "140.Geometric Height",
                    "json_value_format": "",
                    "mandatory": false,
                    "unit": "Feet"
                }
            },
            "JSONDataMapping120": {
                "parameters": {
                    "active": true,
                    "append_value": false,
                    "comment": "Type number, value 33503.015625",
                    "db_content_name": "CAT021",
                    "db_content_variable_name": "ToMR Position",
                    "dimension": "Time",
                    "format_data_type": "",
                    "in_array": false,
                    "json_key": "073.Time of Message Reception for Position",
                    "json_value_format": "",
                    "mandatory": false,
                    "unit": "Second"
                }
            },
            "JSONDataMapping121": {
                "parameters": {
                    "active": true,
                    "append_value": false,
                    "comment": "Type number, value 32398.7265625",
                    "db_content_name": "CAT021",
                    "db_content_variable_name": "ToA Position",
                    "dimension": "Time",
                    "format_data_type": "",
                    "in_array": false,
                    "json_key": "071.Time of Applicability for Position",
                    "json_value_format": "",
                    "mandatory": false,
                    "unit": "Second"
                }
            },
            "JSONDataMapping122": {
                "parameters": {
                    "active": true,
                    "append_value": false,
                    "comment": "Type number, value 60.88485702127616",
                    "db_content_name": "CAT021",
                    "db_content_variable_name": "Latitude HR",
                    "dimension": "Angle",
                    "format_data_type": "",
                    "in_array": false,
                    "json_key": "131.Latitude",
                    "json_value_format": "",
                    "mandatory": false,
                    "unit": "Degree"
                }
            },
            "JSONDataMapping123": {
                "parameters": {
                    "active": true,
                    "append_value": false,
                    "comment": "Type number, value -50.84131700891701",
                    "db_content_name": "CAT021",
                    "db_content_variable_name": "Longitude HR",
                    "dimension": "Angle",
                    "format_data_type": "",
                    "in_array": false,
                    "json_key": "131.Longitude",
                    "json_value_format": "",
                    "mandatory": false,
                    "unit": "Degree"
                }
            },
            "JSONDataMapping124": {
                "parameters": {
                    "active": true,
                    "append_value": false,
                    "comment": "Type number, value 0",
                    "db_content_name": "CAT021",
                    "db_content_variable_name": "Military emergency",
                    "dimension": "",
                    "format_data_type": "",
                    "in_array": false,
                    "json_key": "200.ME",
                    "json_value_format": "",
                    "mandatory": false,
                    "unit": ""
                }
            },
            "JSONDataMapping125": {
                "parameters": {
                    "active": true,
                    "append_value": false,
                    "comment": "Type number, value 0.0",
                    "db_content_name": "CAT021",
                    "db_content_variable_name": "TRD Age",
                    "dimension": "Time",
                    "format_data_type": "",
                    "in_array": false,
                    "json_key": "295.Target Report Descriptor.Age",
                    "json_value_format": "",
                    "mandatory": false,
                    "unit": "Second"
                }
            },
            "JSONDataMapping126": {
                "parameters": {
                    "active": true,
                    "append_value": false,
                    "comment": "Type number, value 0",
                    "db_content_name": "CAT021",
                    "db_content_variable_name": "Receiver ID",
                    "dimension": "",
                    "format_data_type": "",
                    "in_array": false,
                    "json_key": "400.RID",
                    "json_value_format": "",
                    "mandatory": false,
                    "unit": ""
                }
            },
            "JSONDataMapping128": {
                "parameters": {
                    "active": true,
                    "append_value": false,
                    "comment": "",
                    "db_content_name": "CAT021",
                    "db_content_variable_name": "Time of Day",
                    "dimension": "Time",
                    "format_data_type": "",
                    "in_array": false,
                    "json_key": "030.Time of Day",
                    "json_value_format": "",
                    "mandatory": false,
                    "unit": "Second"
                }
            },
            "JSONDataMapping129": {
                "parameters": {
                    "active": true,
                    "append_value": false,
                    "comment": "",
                    "db_content_name": "CAT021",
                    "db_content_variable_name": "Time of Day Accuracy",
                    "dimension": "Time",
                    "format_data_type": "",
                    "in_array": false,
                    "json_key": "032.Time of Day Accuracy",
                    "json_value_format": "",
                    "mandatory": false,
                    "unit": "Second"
                }
            },
            "JSONDataMapping130": {
                "parameters": {
                    "active": true,
                    "append_value": false,
                    "comment": "",
                    "db_content_name": "CAT021",
                    "db_content_variable_name": "CPR Valid",
                    "dimension": "",
                    "format_data_type": "BOOL",
                    "in_array": false,
                    "json_key": "040.CPR",
                    "json_value_format": "invert",
                    "mandatory": false,
                    "unit": ""
                }
            },
            "JSONDataMapping131": {
                "parameters": {
                    "active": true,
                    "append_value": false,
                    "comment": "",
                    "db_content_name": "CAT021",
                    "db_content_variable_name": "Position Check Failed",
                    "dimension": "",
                    "format_data_type": "",
                    "in_array": false,
                    "json_key": "040.IPC",
                    "json_value_format": "",
                    "mandatory": false,
                    "unit": ""
                }
            },
            "JSONDataMapping132": {
                "parameters": {
                    "active": true,
                    "append_value": false,
                    "comment": "",
                    "db_content_name": "CAT021",
                    "db_content_variable_name": "Local Decoding Position Jump",
                    "dimension": "",
                    "format_data_type": "",
                    "in_array": false,
                    "json_key": "040.LDPJ",
                    "json_value_format": "",
                    "mandatory": false,
                    "unit": ""
                }
            },
            "JSONDataMapping133": {
                "parameters": {
                    "active": true,
                    "append_value": false,
                    "comment": "",
                    "db_content_name": "CAT021",
                    "db_content_variable_name": "List Lookup Check Failed",
                    "dimension": "",
                    "format_data_type": "",
                    "in_array": false,
                    "json_key": "040.LLC",
                    "json_value_format": "",
                    "mandatory": false,
                    "unit": ""
                }
            },
            "JSONDataMapping134": {
                "parameters": {
                    "active": true,
                    "append_value": false,
                    "comment": "",
                    "db_content_name": "CAT021",
                    "db_content_variable_name": "No-Go Bit ",
                    "dimension": "",
                    "format_data_type": "",
                    "in_array": false,
                    "json_key": "040.NOGO",
                    "json_value_format": "",
                    "mandatory": false,
                    "unit": ""
                }
            },
            "JSONDataMapping135": {
                "parameters": {
                    "active": true,
                    "append_value": false,
                    "comment": "",
                    "db_content_name": "CAT021",
                    "db_content_variable_name": "Range Check Failed",
                    "dimension": "",
                    "format_data_type": "",
                    "in_array": false,
                    "json_key": "040.RCF",
                    "json_value_format": "",
                    "mandatory": false,
                    "unit": ""
                }
            },
            "JSONDataMapping136": {
                "parameters": {
                    "active": true,
                    "append_value": false,
                    "comment": "",
                    "db_content_name": "CAT021",
                    "db_content_variable_name": "SPI",
                    "dimension": "",
                    "format_data_type": "",
                    "in_array": false,
                    "json_key": "040.SPI",
                    "json_value_format": "",
                    "mandatory": false,
                    "unit": ""
                }
            },
            "JSONDataMapping137": {
                "parameters": {
                    "active": true,
                    "append_value": false,
                    "comment": "",
                    "db_content_name": "CAT021",
                    "db_content_variable_name": "Mode 3/A Garbled",
                    "dimension": "",
                    "format_data_type": "",
                    "in_array": false,
                    "json_key": "070.G",
                    "json_value_format": "",
                    "mandatory": false,
                    "unit": ""
                }
            },
            "JSONDataMapping138": {
                "parameters": {
                    "active": true,
                    "append_value": false,
                    "comment": "",
                    "db_content_name": "CAT021",
                    "db_content_variable_name": "Mode 3/A Smoothed",
                    "dimension": "",
                    "format_data_type": "",
                    "in_array": false,
                    "json_key": "070.L",
                    "json_value_format": "",
                    "mandatory": false,
                    "unit": ""
                }
            },
            "JSONDataMapping139": {
                "parameters": {
                    "active": true,
                    "append_value": false,
                    "comment": "",
                    "db_content_name": "CAT021",
                    "db_content_variable_name": "Mode 3/A Valid",
                    "dimension": "",
                    "format_data_type": "BOOL",
                    "in_array": false,
                    "json_key": "070.V",
                    "json_value_format": "invert",
                    "mandatory": false,
                    "unit": ""
                }
            },
            "JSONDataMapping14": {
                "parameters": {
                    "active": true,
                    "append_value": false,
                    "comment": "Type number, value 0",
                    "db_content_name": "CAT021",
                    "db_content_variable_name": "ACAD Type",
                    "dimension": "",
                    "format_data_type": "",
                    "in_array": false,
                    "json_key": "040.ATP",
                    "json_value_format": "",
                    "mandatory": false,
                    "unit": ""
                }
            },
            "JSONDataMapping140": {
                "parameters": {
                    "active": true,
                    "append_value": false,
                    "comment": "",
                    "db_content_name": "CAT021",
                    "db_content_variable_name": "ToA Velocity",
                    "dimension": "Time",
                    "format_data_type": "",
                    "in_array": false,
                    "json_key": "072.Time of Applicability for Velocity",
                    "json_value_format": "",
                    "mandatory": false,
                    "unit": "Second"
                }
            },
            "JSONDataMapping141": {
                "parameters": {
                    "active": true,
                    "append_value": false,
                    "comment": "",
                    "db_content_name": "CAT021",
                    "db_content_variable_name": "ACAS Status",
                    "dimension": "",
                    "format_data_type": "",
                    "in_array": false,
                    "json_key": "090.AC",
                    "json_value_format": "",
                    "mandatory": false,
                    "unit": ""
                }
            },
            "JSONDataMapping143": {
                "parameters": {
                    "active": true,
                    "append_value": false,
                    "comment": "",
                    "db_content_name": "CAT021",
                    "db_content_variable_name": "Multiple Navigational Aids",
                    "dimension": "",
                    "format_data_type": "",
                    "in_array": false,
                    "json_key": "090.MN",
                    "json_value_format": "",
                    "mandatory": false,
                    "unit": ""
                }
            },
            "JSONDataMapping147": {
                "parameters": {
                    "active": true,
                    "append_value": false,
                    "comment": "",
                    "db_content_name": "CAT021",
                    "db_content_variable_name": "FS SA",
                    "dimension": "Height",
                    "format_data_type": "",
                    "in_array": false,
                    "json_key": "148.Altitude",
                    "json_value_format": "",
                    "mandatory": false,
                    "unit": "Feet"
                }
            },
            "JSONDataMapping148": {
                "parameters": {
                    "active": true,
                    "append_value": false,
                    "comment": "",
                    "db_content_name": "CAT021",
                    "db_content_variable_name": "FS SA AH",
                    "dimension": "",
                    "format_data_type": "",
                    "in_array": false,
                    "json_key": "148.AH",
                    "json_value_format": "",
                    "mandatory": false,
                    "unit": ""
                }
            },
            "JSONDataMapping149": {
                "parameters": {
                    "active": true,
                    "append_value": false,
                    "comment": "",
                    "db_content_name": "CAT021",
                    "db_content_variable_name": "FS SA AM",
                    "dimension": "",
                    "format_data_type": "",
                    "in_array": false,
                    "json_key": "148.AM",
                    "json_value_format": "",
                    "mandatory": false,
                    "unit": ""
                }
            },
            "JSONDataMapping15": {
                "parameters": {
                    "active": true,
                    "append_value": false,
                    "comment": "Type number, value 0",
                    "db_content_name": "CAT021",
                    "db_content_variable_name": "Differential Correction",
                    "dimension": "",
                    "format_data_type": "",
                    "in_array": false,
                    "json_key": "040.DCR",
                    "json_value_format": "",
                    "mandatory": false,
                    "unit": ""
                }
            },
            "JSONDataMapping150": {
                "parameters": {
                    "active": true,
                    "append_value": false,
                    "comment": "",
                    "db_content_name": "CAT021",
                    "db_content_variable_name": "FS SA MV",
                    "dimension": "",
                    "format_data_type": "",
                    "in_array": false,
                    "json_key": "148.MV",
                    "json_value_format": "",
                    "mandatory": false,
                    "unit": ""
                }
            },
            "JSONDataMapping152": {
                "parameters": {
                    "active": true,
                    "append_value": false,
                    "comment": "",
                    "db_content_name": "CAT021",
                    "db_content_variable_name": "Surveillance Status",
                    "dimension": "",
                    "format_data_type": "",
                    "in_array": false,
                    "json_key": "200.SS",
                    "json_value_format": "",
                    "mandatory": false,
                    "unit": ""
                }
            },
            "JSONDataMapping153": {
                "parameters": {
                    "active": true,
                    "append_value": false,
                    "comment": "",
                    "db_content_name": "CAT021",
                    "db_content_variable_name": "MET Temperature",
                    "dimension": "",
                    "format_data_type": "",
                    "in_array": false,
                    "json_key": "220.TMP.Temperature",
                    "json_value_format": "",
                    "mandatory": false,
                    "unit": ""
                }
            },
            "JSONDataMapping154": {
                "parameters": {
                    "active": true,
                    "append_value": false,
                    "comment": "",
                    "db_content_name": "CAT021",
                    "db_content_variable_name": "MET Turbulence",
                    "dimension": "",
                    "format_data_type": "",
                    "in_array": false,
                    "json_key": "220.TRB.Turbulence",
                    "json_value_format": "",
                    "mandatory": false,
                    "unit": ""
                }
            },
            "JSONDataMapping155": {
                "parameters": {
                    "active": true,
                    "append_value": false,
                    "comment": "",
                    "db_content_name": "CAT021",
                    "db_content_variable_name": "MET Wind Direction",
                    "dimension": "",
                    "format_data_type": "",
                    "in_array": false,
                    "json_key": "220.WD.Wind Direction",
                    "json_value_format": "",
                    "mandatory": false,
                    "unit": ""
                }
            },
            "JSONDataMapping156": {
                "parameters": {
                    "active": true,
                    "append_value": false,
                    "comment": "",
                    "db_content_name": "CAT021",
                    "db_content_variable_name": "MET Wind Speed",
                    "dimension": "",
                    "format_data_type": "",
                    "in_array": false,
                    "json_key": "220.WS.Wind Speed",
                    "json_value_format": "",
                    "mandatory": false,
                    "unit": ""
                }
            },
            "JSONDataMapping157": {
                "parameters": {
                    "active": true,
                    "append_value": false,
                    "comment": "",
                    "db_content_name": "CAT021",
                    "db_content_variable_name": "Air Speed Age",
                    "dimension": "Time",
                    "format_data_type": "",
                    "in_array": false,
                    "json_key": "295.Air Speed.Age",
                    "json_value_format": "",
                    "mandatory": false,
                    "unit": "Second"
                }
            },
            "JSONDataMapping158": {
                "parameters": {
                    "active": true,
                    "append_value": false,
                    "comment": "",
                    "db_content_name": "CAT021",
                    "db_content_variable_name": "FS SA Age",
                    "dimension": "Time",
                    "format_data_type": "",
                    "in_array": false,
                    "json_key": "295.Final State Selected Altitude.Age",
                    "json_value_format": "",
                    "mandatory": false,
                    "unit": "Second"
                }
            },
            "JSONDataMapping159": {
                "parameters": {
                    "active": true,
                    "append_value": false,
                    "comment": "",
                    "db_content_name": "CAT021",
                    "db_content_variable_name": "Mode C Code Age",
                    "dimension": "Time",
                    "format_data_type": "",
                    "in_array": false,
                    "json_key": "295.Flight Level.Age",
                    "json_value_format": "",
                    "mandatory": false,
                    "unit": "Second"
                }
            },
            "JSONDataMapping16": {
                "parameters": {
                    "active": true,
                    "append_value": false,
                    "comment": "Type number, value 0",
                    "db_content_name": "CAT021",
                    "db_content_variable_name": "MOPS Version",
                    "dimension": "",
                    "format_data_type": "",
                    "in_array": false,
                    "json_key": "210.VN",
                    "json_value_format": "",
                    "mandatory": false,
                    "unit": ""
                }
            },
            "JSONDataMapping160": {
                "parameters": {
                    "active": true,
                    "append_value": false,
                    "comment": "",
                    "db_content_name": "CAT021",
                    "db_content_variable_name": "Magnetic Heading Age",
                    "dimension": "Time",
                    "format_data_type": "",
                    "in_array": false,
                    "json_key": "295.Magnetic Heading.Age",
                    "json_value_format": "",
                    "mandatory": false,
                    "unit": "Second"
                }
            },
            "JSONDataMapping161": {
                "parameters": {
                    "active": true,
                    "append_value": false,
                    "comment": "",
                    "db_content_name": "CAT021",
                    "db_content_variable_name": "Message Amplitude Age",
                    "dimension": "Time",
                    "format_data_type": "",
                    "in_array": false,
                    "json_key": "295.Message Amplitude.Age",
                    "json_value_format": "",
                    "mandatory": false,
                    "unit": "Second"
                }
            },
            "JSONDataMapping162": {
                "parameters": {
                    "active": true,
                    "append_value": false,
                    "comment": "",
                    "db_content_name": "CAT021",
                    "db_content_variable_name": "MET Age",
                    "dimension": "Time",
                    "format_data_type": "",
                    "in_array": false,
                    "json_key": "295.Met Information.Age",
                    "json_value_format": "",
                    "mandatory": false,
                    "unit": "Second"
                }
            },
            "JSONDataMapping163": {
                "parameters": {
                    "active": true,
                    "append_value": false,
                    "comment": "",
                    "db_content_name": "CAT021",
                    "db_content_variable_name": "Roll Angle Age",
                    "dimension": "Time",
                    "format_data_type": "",
                    "in_array": false,
                    "json_key": "295.Roll Angle.Age",
                    "json_value_format": "",
                    "mandatory": false,
                    "unit": "Second"
                }
            },
            "JSONDataMapping164": {
                "parameters": {
                    "active": true,
                    "append_value": false,
                    "comment": "",
                    "db_content_name": "CAT021",
                    "db_content_variable_name": "Track Angle Rate Age",
                    "dimension": "Time",
                    "format_data_type": "",
                    "in_array": false,
                    "json_key": "295.Track Angle Rate.Age",
                    "json_value_format": "",
                    "mandatory": false,
                    "unit": "Second"
                }
            },
            "JSONDataMapping165": {
                "parameters": {
                    "active": true,
                    "append_value": false,
                    "comment": "",
                    "db_content_name": "CAT021",
                    "db_content_variable_name": "True Air Speed Age",
                    "dimension": "Time",
                    "format_data_type": "",
                    "in_array": false,
                    "json_key": "295.True Air Speed.Age",
                    "json_value_format": "",
                    "mandatory": false,
                    "unit": "Second"
                }
            },
            "JSONDataMapping166": {
                "parameters": {
                    "active": true,
                    "append_value": false,
                    "comment": "Type number, value 32398.7265625",
                    "db_content_name": "CAT021",
                    "db_content_variable_name": "Time of Day",
                    "dimension": "Time",
                    "format_data_type": "",
                    "in_array": false,
                    "json_key": "073.Time of Message Reception for Position",
                    "json_value_format": "",
                    "mandatory": false,
                    "unit": "Second"
                }
            },
            "JSONDataMapping167": {
                "parameters": {
                    "active": true,
                    "append_value": false,
                    "comment": "Line Identifer",
                    "db_content_name": "CAT021",
                    "db_content_variable_name": "Line ID",
                    "dimension": "",
                    "format_data_type": "",
                    "in_array": false,
                    "json_key": "line_id",
                    "json_value_format": "",
                    "mandatory": false,
                    "unit": ""
                }
            },
            "JSONDataMapping17": {
                "parameters": {
                    "active": true,
                    "append_value": false,
                    "comment": "Type number, value 3",
                    "db_content_name": "CAT021",
                    "db_content_variable_name": "Emitter Category",
                    "dimension": "",
                    "format_data_type": "",
                    "in_array": false,
                    "json_key": "020.ECAT",
                    "json_value_format": "",
                    "mandatory": false,
                    "unit": ""
                }
            },
            "JSONDataMapping18": {
                "parameters": {
                    "active": true,
                    "append_value": false,
                    "comment": "Type number, value 0",
                    "db_content_name": "CAT021",
                    "db_content_variable_name": "FFT",
                    "dimension": "",
                    "format_data_type": "",
                    "in_array": false,
                    "json_key": "040.RAB",
                    "json_value_format": "",
                    "mandatory": false,
                    "unit": ""
                }
            },
            "JSONDataMapping19": {
                "parameters": {
                    "active": true,
                    "append_value": false,
                    "comment": "Type number, value 202431.25",
                    "db_content_name": "CAT021",
                    "db_content_variable_name": "Geometric Vertical Rate",
                    "dimension": "",
                    "format_data_type": "",
                    "in_array": false,
                    "json_key": "157.Geometric Vertical Rate",
                    "json_value_format": "",
                    "mandatory": false,
                    "unit": ""
                }
            },
            "JSONDataMapping2": {
                "parameters": {
                    "active": true,
                    "append_value": false,
                    "comment": "Type number, value 50",
                    "db_content_name": "CAT021",
                    "db_content_variable_name": "SAC",
                    "dimension": "",
                    "format_data_type": "",
                    "in_array": false,
                    "json_key": "010.SAC",
                    "json_value_format": "",
                    "mandatory": false,
                    "unit": ""
                }
            },
            "JSONDataMapping20": {
                "parameters": {
                    "active": true,
                    "append_value": false,
                    "comment": "Type number, value 0.1116943245",
                    "db_content_name": "CAT021",
                    "db_content_variable_name": "Ground Speed",
                    "dimension": "Speed",
                    "format_data_type": "",
                    "in_array": false,
                    "json_key": "160.Ground Speed",
                    "json_value_format": "",
                    "mandatory": false,
                    "unit": "NM/Second"
                }
            },
            "JSONDataMapping21": {
                "parameters": {
                    "active": true,
                    "append_value": false,
                    "comment": "Type number, value 0",
                    "db_content_name": "CAT021",
                    "db_content_variable_name": "Ground Bit",
                    "dimension": "",
                    "format_data_type": "",
                    "in_array": false,
                    "json_key": "040.GBS",
                    "json_value_format": "",
                    "mandatory": false,
                    "unit": ""
                }
            },
            "JSONDataMapping22": {
                "parameters": {
                    "active": true,
                    "append_value": false,
                    "comment": "",
                    "db_content_name": "CAT021",
                    "db_content_variable_name": "Magnetic Heading",
                    "dimension": "Angle",
                    "format_data_type": "",
                    "in_array": false,
                    "json_key": "152.Magnetic Heading",
                    "json_value_format": "",
                    "mandatory": false,
                    "unit": "Degree"
                }
            },
            "JSONDataMapping23": {
                "parameters": {
                    "active": true,
                    "append_value": false,
                    "comment": "",
                    "db_content_name": "CAT021",
                    "db_content_variable_name": "Roll Angle",
                    "dimension": "",
                    "format_data_type": "",
                    "in_array": false,
                    "json_key": "230.Roll Angle",
                    "json_value_format": "",
                    "mandatory": false,
                    "unit": ""
                }
            },
            "JSONDataMapping24": {
                "parameters": {
                    "active": true,
                    "append_value": false,
                    "comment": "Type number, value 0",
                    "db_content_name": "CAT021",
                    "db_content_variable_name": "Simulated",
                    "dimension": "",
                    "format_data_type": "",
                    "in_array": false,
                    "json_key": "040.SIM",
                    "json_value_format": "",
                    "mandatory": false,
                    "unit": ""
                }
            },
            "JSONDataMapping25": {
                "parameters": {
                    "active": true,
                    "append_value": false,
                    "comment": "Type number, value 10",
                    "db_content_name": "CAT021",
                    "db_content_variable_name": "NACp",
                    "dimension": "",
                    "format_data_type": "",
                    "in_array": false,
                    "json_key": "090.NACp",
                    "json_value_format": "",
                    "mandatory": false,
                    "unit": ""
                }
            },
            "JSONDataMapping27": {
                "parameters": {
                    "active": true,
                    "append_value": false,
                    "comment": "Type number, value 0",
                    "db_content_name": "CAT021",
                    "db_content_variable_name": "Priority Status",
                    "dimension": "",
                    "format_data_type": "",
                    "in_array": false,
                    "json_key": "200.PS",
                    "json_value_format": "",
                    "mandatory": false,
                    "unit": ""
                }
            },
            "JSONDataMapping28": {
                "parameters": {
                    "active": true,
                    "append_value": false,
                    "comment": "Type number, value 0",
                    "db_content_name": "CAT021",
                    "db_content_variable_name": "Test",
                    "dimension": "",
                    "format_data_type": "",
                    "in_array": false,
                    "json_key": "040.TST",
                    "json_value_format": "",
                    "mandatory": false,
                    "unit": ""
                }
            },
            "JSONDataMapping29": {
                "parameters": {
                    "active": true,
                    "append_value": false,
                    "comment": "Type number, value 102.2003173363",
                    "db_content_name": "CAT021",
                    "db_content_variable_name": "Track Angle",
                    "dimension": "Angle",
                    "format_data_type": "",
                    "in_array": false,
                    "json_key": "160.Track Angle",
                    "json_value_format": "",
                    "mandatory": false,
                    "unit": "Degree"
                }
            },
            "JSONDataMapping3": {
                "parameters": {
                    "active": true,
                    "append_value": false,
                    "comment": "Type number, value 80",
                    "db_content_name": "CAT021",
                    "db_content_variable_name": "SIC",
                    "dimension": "",
                    "format_data_type": "",
                    "in_array": false,
                    "json_key": "010.SIC",
                    "json_value_format": "",
                    "mandatory": false,
                    "unit": ""
                }
            },
            "JSONDataMapping31": {
                "parameters": {
                    "active": true,
                    "append_value": false,
                    "comment": "",
                    "db_content_name": "CAT021",
                    "db_content_variable_name": "Track Angle Rate",
                    "dimension": "",
                    "format_data_type": "",
                    "in_array": false,
                    "json_key": "165.TAR",
                    "json_value_format": "",
                    "mandatory": false,
                    "unit": ""
                }
            },
            "JSONDataMapping32": {
                "parameters": {
                    "active": true,
                    "append_value": false,
                    "comment": "Type number, value 0",
                    "db_content_name": "CAT021",
                    "db_content_variable_name": "NUCr or NACv",
                    "dimension": "",
                    "format_data_type": "",
                    "in_array": false,
                    "json_key": "090.NUCr or NACv",
                    "json_value_format": "",
                    "mandatory": false,
                    "unit": ""
                }
            },
            "JSONDataMapping33": {
                "parameters": {
                    "active": true,
                    "append_value": false,
                    "comment": "Type number, value 0",
                    "db_content_name": "CAT021",
                    "db_content_variable_name": "Service Identification",
                    "dimension": "",
                    "format_data_type": "",
                    "in_array": false,
                    "json_key": "015.Service Identification",
                    "json_value_format": "",
                    "mandatory": false,
                    "unit": ""
                }
            },
            "JSONDataMapping34": {
                "parameters": {
                    "active": true,
                    "append_value": false,
                    "comment": "Type number, value 2.0, not found in SCDB",
                    "db_content_name": "CAT021",
                    "db_content_variable_name": "Report Period",
                    "dimension": "",
                    "format_data_type": "",
                    "in_array": false,
                    "json_key": "016.RP",
                    "json_value_format": "",
                    "mandatory": false,
                    "unit": ""
                }
            },
            "JSONDataMapping35": {
                "parameters": {
                    "active": true,
                    "append_value": false,
                    "comment": "Type number, value 0",
                    "db_content_name": "CAT021",
                    "db_content_variable_name": "Altitude Reporting Capability",
                    "dimension": "",
                    "format_data_type": "",
                    "in_array": false,
                    "json_key": "040.ARC",
                    "json_value_format": "",
                    "mandatory": false,
                    "unit": ""
                }
            },
            "JSONDataMapping36": {
                "parameters": {
                    "active": true,
                    "append_value": false,
                    "comment": "Type number, value 0, not found in SCDB",
                    "db_content_name": "CAT021",
                    "db_content_variable_name": "Confidence Level",
                    "dimension": "",
                    "format_data_type": "",
                    "in_array": false,
                    "json_key": "040.CL",
                    "json_value_format": "",
                    "mandatory": false,
                    "unit": ""
                }
            },
            "JSONDataMapping39": {
                "parameters": {
                    "active": true,
                    "append_value": false,
                    "comment": "Type number, value 0 not found in SCDB",
                    "db_content_name": "CAT021",
                    "db_content_variable_name": "Range Check Passed",
                    "dimension": "",
                    "format_data_type": "",
                    "in_array": false,
                    "json_key": "040.RC",
                    "json_value_format": "",
                    "mandatory": false,
                    "unit": ""
                }
            },
            "JSONDataMapping4": {
                "parameters": {
                    "active": true,
                    "append_value": false,
                    "comment": "Type number, value 4953742",
                    "db_content_name": "CAT021",
                    "db_content_variable_name": "Aircraft Address",
                    "dimension": "",
                    "format_data_type": "",
                    "in_array": false,
                    "json_key": "080.Target Address",
                    "json_value_format": "",
                    "mandatory": false,
                    "unit": ""
                }
            },
            "JSONDataMapping40": {
                "parameters": {
                    "active": true,
                    "append_value": false,
                    "comment": "Type number, value 1",
                    "db_content_name": "CAT021",
                    "db_content_variable_name": "Selected Altitude Available",
                    "dimension": "",
                    "format_data_type": "BOOL",
                    "in_array": false,
                    "json_key": "040.SAA",
                    "json_value_format": "invert",
                    "mandatory": false,
                    "unit": ""
                }
            },
            "JSONDataMapping41": {
                "parameters": {
                    "active": true,
                    "append_value": false,
                    "comment": "Type number, value 3277",
                    "db_content_name": "CAT021",
                    "db_content_variable_name": "Mode 3/A Code",
                    "dimension": "",
                    "format_data_type": "INT",
                    "in_array": false,
                    "json_key": "070.Mode-3/A",
                    "json_value_format": "octal",
                    "mandatory": false,
                    "unit": ""
                }
            },
            "JSONDataMapping42": {
                "parameters": {
                    "active": true,
                    "append_value": false,
                    "comment": "Type number, value 33502.75, unsure if correct mapping",
                    "db_content_name": "CAT021",
                    "db_content_variable_name": "ToMRv",
                    "dimension": "Time",
                    "format_data_type": "",
                    "in_array": false,
                    "json_key": "075.Time of Message Reception of Velocity",
                    "json_value_format": "",
                    "mandatory": false,
                    "unit": "Second"
                }
            },
            "JSONDataMapping43": {
                "parameters": {
                    "active": true,
                    "append_value": false,
                    "comment": "Type number, value 33503.1328125, unsure where to map",
                    "db_content_name": "CAT021",
                    "db_content_variable_name": "ToRT",
                    "dimension": "Time",
                    "format_data_type": "",
                    "in_array": false,
                    "json_key": "077.Time Of ASTERIX Report Transmission",
                    "json_value_format": "",
                    "mandatory": false,
                    "unit": "Second"
                }
            },
            "JSONDataMapping45": {
                "parameters": {
                    "active": true,
                    "append_value": false,
                    "comment": "Type number, value 7",
                    "db_content_name": "CAT021",
                    "db_content_variable_name": "NUCp or NIC",
                    "dimension": "",
                    "format_data_type": "",
                    "in_array": false,
                    "json_key": "090.NUCp or NIC",
                    "json_value_format": "",
                    "mandatory": false,
                    "unit": ""
                }
            },
            "JSONDataMapping46": {
                "parameters": {
                    "active": true,
                    "append_value": false,
                    "comment": "Type number, value 365, not found in SCDB",
                    "db_content_name": "CAT021",
                    "db_content_variable_name": "Track Number",
                    "dimension": "",
                    "format_data_type": "",
                    "in_array": false,
                    "json_key": "161.Track Number",
                    "json_value_format": "",
                    "mandatory": false,
                    "unit": ""
                }
            },
            "JSONDataMapping47": {
                "parameters": {
                    "active": true,
                    "append_value": false,
                    "comment": "Type number, value 0 not found in SCDB",
                    "db_content_name": "CAT021",
                    "db_content_variable_name": "Intent Change Flag",
                    "dimension": "",
                    "format_data_type": "",
                    "in_array": false,
                    "json_key": "200.ICF",
                    "json_value_format": "",
                    "mandatory": false,
                    "unit": ""
                }
            },
            "JSONDataMapping48": {
                "parameters": {
                    "active": true,
                    "append_value": false,
                    "comment": "Type number, value 0 not found in SCDB",
                    "db_content_name": "CAT021",
                    "db_content_variable_name": "LNAV Mode",
                    "dimension": "",
                    "format_data_type": "",
                    "in_array": false,
                    "json_key": "200.LNAV",
                    "json_value_format": "",
                    "mandatory": false,
                    "unit": ""
                }
            },
            "JSONDataMapping5": {
                "parameters": {
                    "active": true,
                    "append_value": false,
                    "comment": "Type string, value \"KKK1CF  \"",
                    "db_content_name": "CAT021",
                    "db_content_variable_name": "Aircraft Identification",
                    "dimension": "",
                    "format_data_type": "",
                    "in_array": false,
                    "json_key": "170.Target Identification",
                    "json_value_format": "",
                    "mandatory": false,
                    "unit": ""
                }
            },
            "JSONDataMapping50": {
                "parameters": {
                    "active": true,
                    "append_value": false,
                    "comment": "Type number, value 0 not found in SCDB",
                    "db_content_name": "CAT021",
                    "db_content_variable_name": "Version Not Supported",
                    "dimension": "",
                    "format_data_type": "",
                    "in_array": false,
                    "json_key": "210.VNS",
                    "json_value_format": "",
                    "mandatory": false,
                    "unit": ""
                }
            },
            "JSONDataMapping53": {
                "parameters": {
                    "active": true,
                    "append_value": false,
                    "comment": "Type number, value 1",
                    "db_content_name": "CAT021",
                    "db_content_variable_name": "NICbaro",
                    "dimension": "",
                    "format_data_type": "",
                    "in_array": false,
                    "json_key": "090.NICbaro",
                    "json_value_format": "",
                    "mandatory": false,
                    "unit": ""
                }
            },
            "JSONDataMapping54": {
                "parameters": {
                    "active": true,
                    "append_value": false,
                    "comment": "Type number, value 2",
                    "db_content_name": "CAT021",
                    "db_content_variable_name": "SIL",
                    "dimension": "",
                    "format_data_type": "",
                    "in_array": false,
                    "json_key": "090.SIL",
                    "json_value_format": "",
                    "mandatory": false,
                    "unit": ""
                }
            },
            "JSONDataMapping55": {
                "parameters": {
                    "active": true,
                    "append_value": false,
                    "comment": "Type number, value 0",
                    "db_content_name": "CAT021",
                    "db_content_variable_name": "Geometric Vertical Rate RE",
                    "dimension": "",
                    "format_data_type": "",
                    "in_array": false,
                    "json_key": "157.RE",
                    "json_value_format": "",
                    "mandatory": false,
                    "unit": ""
                }
            },
            "JSONDataMapping56": {
                "parameters": {
                    "active": true,
                    "append_value": false,
                    "comment": "Type number, value 0",
                    "db_content_name": "CAT021",
                    "db_content_variable_name": "Ground Speed RE",
                    "dimension": "",
                    "format_data_type": "",
                    "in_array": false,
                    "json_key": "160.RE",
                    "json_value_format": "",
                    "mandatory": false,
                    "unit": ""
                }
            },
            "JSONDataMapping57": {
                "parameters": {
                    "active": true,
                    "append_value": false,
                    "comment": "Type number, value 1918.75",
                    "db_content_name": "CAT021",
                    "db_content_variable_name": "Barometric Vertical Rate",
                    "dimension": "",
                    "format_data_type": "",
                    "in_array": false,
                    "json_key": "155.Barometric Vertical Rate",
                    "json_value_format": "",
                    "mandatory": false,
                    "unit": ""
                }
            },
            "JSONDataMapping58": {
                "parameters": {
                    "active": true,
                    "append_value": false,
                    "comment": "Type number, value 0",
                    "db_content_name": "CAT021",
                    "db_content_variable_name": "Barometric Vertical Rate RE",
                    "dimension": "",
                    "format_data_type": "",
                    "in_array": false,
                    "json_key": "155.RE",
                    "json_value_format": "",
                    "mandatory": false,
                    "unit": ""
                }
            },
            "JSONDataMapping59": {
                "parameters": {
                    "active": true,
                    "append_value": false,
                    "comment": "Type number, value 0",
                    "db_content_name": "CAT021",
                    "db_content_variable_name": "True Airspeed RE",
                    "dimension": "",
                    "format_data_type": "",
                    "in_array": false,
                    "json_key": "151.RE",
                    "json_value_format": "",
                    "mandatory": false,
                    "unit": ""
                }
            },
            "JSONDataMapping6": {
                "parameters": {
                    "active": true,
                    "append_value": false,
                    "comment": "Type number, value 340.25",
                    "db_content_name": "CAT021",
                    "db_content_variable_name": "Mode C Code",
                    "dimension": "Height",
                    "format_data_type": "",
                    "in_array": false,
                    "json_key": "145.Flight Level",
                    "json_value_format": "",
                    "mandatory": false,
                    "unit": "Flight Level"
                }
            },
            "JSONDataMapping60": {
                "parameters": {
                    "active": true,
                    "append_value": false,
                    "comment": "Type number, value 150.0",
                    "db_content_name": "CAT021",
                    "db_content_variable_name": "True Airspeed",
                    "dimension": "Speed",
                    "format_data_type": "",
                    "in_array": false,
                    "json_key": "151.True Air Speed",
                    "json_value_format": "",
                    "mandatory": false,
                    "unit": "Knots"
                }
            },
            "JSONDataMapping62": {
                "parameters": {
                    "active": true,
                    "append_value": false,
                    "comment": "Type number, value 0",
                    "db_content_name": "CAT021",
                    "db_content_variable_name": "Air Speed",
                    "dimension": "",
                    "format_data_type": "",
                    "in_array": false,
                    "json_key": "150.Air Speed",
                    "json_value_format": "",
                    "mandatory": false,
                    "unit": ""
                }
            },
            "JSONDataMapping68": {
                "parameters": {
                    "active": true,
                    "append_value": false,
                    "comment": "Type string, value \"89acebdd\"",
                    "db_content_name": "CAT021",
                    "db_content_variable_name": "ARTAS Hash",
                    "dimension": "",
                    "format_data_type": "",
                    "in_array": false,
                    "json_key": "artas_md5",
                    "json_value_format": "",
                    "mandatory": false,
                    "unit": ""
                }
            },
            "JSONDataMapping7": {
                "parameters": {
                    "active": true,
                    "append_value": false,
                    "comment": "Type number, value 48.17834855158",
                    "db_content_name": "CAT021",
                    "db_content_variable_name": "Latitude",
                    "dimension": "Angle",
                    "format_data_type": "",
                    "in_array": false,
                    "json_key": "130.Latitude",
                    "json_value_format": "",
                    "mandatory": false,
                    "unit": "Degree"
                }
            },
            "JSONDataMapping72": {
                "parameters": {
                    "active": true,
                    "append_value": false,
                    "comment": "Type number, value 0",
                    "db_content_name": "CAT021",
                    "db_content_variable_name": "ARV Capability",
                    "dimension": "",
                    "format_data_type": "",
                    "in_array": false,
                    "json_key": "008.ARV",
                    "json_value_format": "",
                    "mandatory": false,
                    "unit": ""
                }
            },
            "JSONDataMapping73": {
                "parameters": {
                    "active": true,
                    "append_value": false,
                    "comment": "Type number, value 0",
                    "db_content_name": "CAT021",
                    "db_content_variable_name": "Cockpit Display of Traffic Information",
                    "dimension": "",
                    "format_data_type": "",
                    "in_array": false,
                    "json_key": "008.CDTI/A",
                    "json_value_format": "",
                    "mandatory": false,
                    "unit": ""
                }
            },
            "JSONDataMapping74": {
                "parameters": {
                    "active": true,
                    "append_value": false,
                    "comment": "Type number, value 0",
                    "db_content_name": "CAT021",
                    "db_content_variable_name": "TCAS System Status",
                    "dimension": "",
                    "format_data_type": "BOOL",
                    "in_array": false,
                    "json_key": "008.Not TCAS",
                    "json_value_format": "invert",
                    "mandatory": false,
                    "unit": ""
                }
            },
            "JSONDataMapping75": {
                "parameters": {
                    "active": true,
                    "append_value": false,
                    "comment": "Type number, value 0",
                    "db_content_name": "CAT021",
                    "db_content_variable_name": "TCAS Resolution Advisory",
                    "dimension": "",
                    "format_data_type": "",
                    "in_array": false,
                    "json_key": "008.RA",
                    "json_value_format": "",
                    "mandatory": false,
                    "unit": ""
                }
            },
            "JSONDataMapping76": {
                "parameters": {
                    "active": true,
                    "append_value": false,
                    "comment": "Type number, value 1",
                    "db_content_name": "CAT021",
                    "db_content_variable_name": "Single Antenna",
                    "dimension": "",
                    "format_data_type": "",
                    "in_array": false,
                    "json_key": "008.SA",
                    "json_value_format": "",
                    "mandatory": false,
                    "unit": ""
                }
            },
            "JSONDataMapping77": {
                "parameters": {
                    "active": true,
                    "append_value": false,
                    "comment": "Type number, value 0",
                    "db_content_name": "CAT021",
                    "db_content_variable_name": "Trajectory Change Report Capability",
                    "dimension": "",
                    "format_data_type": "",
                    "in_array": false,
                    "json_key": "008.TC",
                    "json_value_format": "",
                    "mandatory": false,
                    "unit": ""
                }
            },
            "JSONDataMapping78": {
                "parameters": {
                    "active": true,
                    "append_value": false,
                    "comment": "Type number, value 0",
                    "db_content_name": "CAT021",
                    "db_content_variable_name": "Target State Report Capability",
                    "dimension": "",
                    "format_data_type": "",
                    "in_array": false,
                    "json_key": "008.TS",
                    "json_value_format": "",
                    "mandatory": false,
                    "unit": ""
                }
            },
            "JSONDataMapping8": {
                "parameters": {
                    "active": true,
                    "append_value": false,
                    "comment": "Type number, value 16.621754912100002",
                    "db_content_name": "CAT021",
                    "db_content_variable_name": "Longitude",
                    "dimension": "Angle",
                    "format_data_type": "",
                    "in_array": false,
                    "json_key": "130.Longitude",
                    "json_value_format": "",
                    "mandatory": false,
                    "unit": "Degree"
                }
            },
            "JSONDataMapping81": {
                "parameters": {
                    "active": true,
                    "append_value": false,
                    "comment": "Type number, value 0",
                    "db_content_name": "CAT021",
                    "db_content_variable_name": "ToMR Position FSI",
                    "dimension": "",
                    "format_data_type": "",
                    "in_array": false,
                    "json_key": "074.FSI",
                    "json_value_format": "",
                    "mandatory": false,
                    "unit": ""
                }
            },
            "JSONDataMapping82": {
                "parameters": {
                    "active": true,
                    "append_value": false,
                    "comment": "Type number, value 0.39351637838965975",
                    "db_content_name": "CAT021",
                    "db_content_variable_name": "ToMR Position HP",
                    "dimension": "Time",
                    "format_data_type": "",
                    "in_array": false,
                    "json_key": "074.Time of Message Reception of Position - high precision",
                    "json_value_format": "",
                    "mandatory": false,
                    "unit": "Second"
                }
            },
            "JSONDataMapping83": {
                "parameters": {
                    "active": true,
                    "append_value": false,
                    "comment": "Type number, value 0",
                    "db_content_name": "CAT021",
                    "db_content_variable_name": "ToMR Velocity FSI",
                    "dimension": "",
                    "format_data_type": "",
                    "in_array": false,
                    "json_key": "076.FSI",
                    "json_value_format": "",
                    "mandatory": false,
                    "unit": ""
                }
            },
            "JSONDataMapping84": {
                "parameters": {
                    "active": true,
                    "append_value": false,
                    "comment": "Type number, value 0.8989372451012015",
                    "db_content_name": "CAT021",
                    "db_content_variable_name": "ToMR Velocity HP",
                    "dimension": "",
                    "format_data_type": "",
                    "in_array": false,
                    "json_key": "076.Time of Message Reception of Velocity - high precision",
                    "json_value_format": "",
                    "mandatory": false,
                    "unit": ""
                }
            },
            "JSONDataMapping87": {
                "parameters": {
                    "active": true,
                    "append_value": false,
                    "comment": "Type number, value 0",
                    "db_content_name": "CAT021",
                    "db_content_variable_name": "Geometric Altitude Accuracy",
                    "dimension": "",
                    "format_data_type": "",
                    "in_array": false,
                    "json_key": "090.GVA",
                    "json_value_format": "",
                    "mandatory": false,
                    "unit": ""
                }
            },
            "JSONDataMapping88": {
                "parameters": {
                    "active": true,
                    "append_value": false,
                    "comment": "Type number, value 10",
                    "db_content_name": "CAT021",
                    "db_content_variable_name": "PIC",
                    "dimension": "",
                    "format_data_type": "",
                    "in_array": false,
                    "json_key": "090.PIC",
                    "json_value_format": "",
                    "mandatory": false,
                    "unit": ""
                }
            },
            "JSONDataMapping89": {
                "parameters": {
                    "active": true,
                    "append_value": false,
                    "comment": "Type number, value 0",
                    "db_content_name": "CAT021",
                    "db_content_variable_name": "SDA",
                    "dimension": "",
                    "format_data_type": "",
                    "in_array": false,
                    "json_key": "090.SDA",
                    "json_value_format": "",
                    "mandatory": false,
                    "unit": ""
                }
            },
            "JSONDataMapping90": {
                "parameters": {
                    "active": true,
                    "append_value": false,
                    "comment": "Type number, value 0",
                    "db_content_name": "CAT021",
                    "db_content_variable_name": "SIL Supplement",
                    "dimension": "",
                    "format_data_type": "",
                    "in_array": false,
                    "json_key": "090.SIL-Supplement",
                    "json_value_format": "",
                    "mandatory": false,
                    "unit": ""
                }
            },
            "JSONDataMapping91": {
                "parameters": {
                    "active": true,
                    "append_value": false,
                    "comment": "Type number, value -87.0",
                    "db_content_name": "CAT021",
                    "db_content_variable_name": "Message Amplitude",
                    "dimension": "",
                    "format_data_type": "",
                    "in_array": false,
                    "json_key": "132.MAM",
                    "json_value_format": "",
                    "mandatory": false,
                    "unit": ""
                }
            },
            "JSONDataMapping97": {
                "parameters": {
                    "active": true,
                    "append_value": false,
                    "comment": "Type number, value 0.5",
                    "db_content_name": "CAT021",
                    "db_content_variable_name": "Geometric Height Age",
                    "dimension": "Time",
                    "format_data_type": "",
                    "in_array": false,
                    "json_key": "295.Geometric Height.Age",
                    "json_value_format": "",
                    "mandatory": false,
                    "unit": "Second"
                }
            },
            "JSONDataMapping98": {
                "parameters": {
                    "active": true,
                    "append_value": false,
                    "comment": "Type number, value 0.5",
                    "db_content_name": "CAT021",
                    "db_content_variable_name": "Geometric Vertical Rate Age",
                    "dimension": "Time",
                    "format_data_type": "",
                    "in_array": false,
                    "json_key": "295.Geometric Vertical Rate.Age",
                    "json_value_format": "",
                    "mandatory": false,
                    "unit": "Second"
                }
            },
            "JSONDataMapping99": {
                "parameters": {
                    "active": true,
                    "append_value": false,
                    "comment": "Type number, value 0.5",
                    "db_content_name": "CAT021",
                    "db_content_variable_name": "Ground Vector Age",
                    "dimension": "Time",
                    "format_data_type": "",
                    "in_array": false,
                    "json_key": "295.Ground Vector.Age",
                    "json_value_format": "",
                    "mandatory": false,
                    "unit": "Second"
                }
            }
        }
    }
}